Workbook

Sheet Position Size
A1: Position Size Calculator
A2: Edit the yellow cells (blue text). Everything else is calculated.
A4: INPUTS
A5: Account balance ($) | B5: 79 | C5: Your $50 start + $29 profit (from you).
A6: Risk per trade (% of account) | B6: 0.05 | C6: How much of the account you accept losing if the stop is hit. 1-2% is standard; 5% is a practical floor on a very small account.
A7: Entry price ($) | B7: 0.2362 | C7: GTC price from your screenshot.
A8: Stop-loss price ($) | B8: 0.22 | C8: Below the most recent pullback low on the chart (example).
A9: Target price ($) | B9: 0.27 | C9: Example: near the 24H spike high.
A10: Fee per side (%) | B10: 0.006 | C10: Assumption: Coinbase Advanced taker fee at the lowest volume tier (~0.6%). Simple Buy/Sell in the app costs more; check your actual fee.
A12: RESULTS
A13: Max $ you're willing to lose | B13: =B5*B6 -> 3.95
A14: Loss per coin if stopped out (incl. fees) | B14: =IF(B7>B8,(B7-B8)+B7*B10+B8*B10,NA()) -> 0.0189372 | C14: Price distance to stop plus the fee paid on both the buy and the sell.
A15: Coins to buy (risk-based) | B15: =IFERROR(B13/B14,0) -> 208.58416
A16: Position size ($) — capped at account balance | B16: =MIN(B15*B7,B5) -> 49.267579 | C16: If the risk-based size is bigger than your account, it's limited to what you have.
A17: Coins to buy (after cap) | B17: =IFERROR(B16/B7,0) -> 208.58416
A18: Position as % of account | B18: =IFERROR(B16/B5,0) -> 0.62364024
A19: Net loss if stop is hit ($) | B19: =-B17*((B7-B8)+B7*B10+B8*B10) -> -3.95
A20: Net profit if target is hit ($) | B20: =B17*((B9-B7)-B7*B10-B9*B10) -> 6.4166329
A21: Reward : risk ratio | B21: =IFERROR(B20/-B19,0) -> 1.624464 | C21: How many dollars you aim to make for each dollar you risk.
A22: Trade worth taking? (needs 2x or better) | B22: =IF(B21>=2,"YES","NO — target too close or stop too wide") -> NO — target too close or stop too wide

Sheet Trade Journal
A1: Trade Journal
A2: Fill in the blue columns for each trade. Grey columns calculate automatically once Exit Price is entered. Row 5 is an example: your GTC position marked at today's $0.2362 — replace it with your real fills.
A4: # | B4: Entry Date | C4: Coin | D4: Entry Price ($) | E4: Stop ($) | F4: Target ($) | G4: Quantity | H4: Cost ($) | I4: Exit Date | J4: Exit Price ($) | K4: Fees ($) | L4: Net P/L ($) | M4: Return % | N4: R Multiple | O4: Planned R:R | P4: Setup / Reason | Q4: Followed Plan? | R4: Notes / Lesson
A5: 1 | B5: 46311 | C5: GTC | D5: 0.1495 | E5: 0.135 | F5: 0.25 | G5: 334.45 | H5: =IF(OR(D5="",G5=""),"",D5*G5) -> 50.000275 | I5: 46312 | J5: 0.2362 | K5: 0 | L5: =IF(OR(J5="",H5=""),"",J5*G5-H5-N(K5)) -> 28.996815 | M5: =IF(L5="","",L5/H5) -> 0.57993311 | N5: =IF(OR(L5="",E5="",D5<=E5),"",L5/((D5-E5)*G5)) -> 5.9793103 | O5: =IF(OR(D5="",E5="",F5="",D5<=E5),"",(F5-D5)/(D5-E5)) -> 6.9310345 | P5: EXAMPLE — entry back-solved from $50 → $79 (+58%) | Q5: Y | R5: Exit = today's price, not a real sale. Replace with your actual numbers.
A6: 2 | H6: =IF(OR(D6="",G6=""),"",D6*G6) | L6: =IF(OR(J6="",H6=""),"",J6*G6-H6-N(K6)) | M6: =IF(L6="","",L6/H6) | N6: =IF(OR(L6="",E6="",D6<=E6),"",L6/((D6-E6)*G6)) | O6: =IF(OR(D6="",E6="",F6="",D6<=E6),"",(F6-D6)/(D6-E6))
A7: 3 | H7: =IF(OR(D7="",G7=""),"",D7*G7) | L7: =IF(OR(J7="",H7=""),"",J7*G7-H7-N(K7)) | M7: =IF(L7="","",L7/H7) | N7: =IF(OR(L7="",E7="",D7<=E7),"",L7/((D7-E7)*G7)) | O7: =IF(OR(D7="",E7="",F7="",D7<=E7),"",(F7-D7)/(D7-E7))
A8: 4 | H8: =IF(OR(D8="",G8=""),"",D8*G8) | L8: =IF(OR(J8="",H8=""),"",J8*G8-H8-N(K8)) | M8: =IF(L8="","",L8/H8) | N8: =IF(OR(L8="",E8="",D8<=E8),"",L8/((D8-E8)*G8)) | O8: =IF(OR(D8="",E8="",F8="",D8<=E8),"",(F8-D8)/(D8-E8))
A9: 5 | H9: =IF(OR(D9="",G9=""),"",D9*G9) | L9: =IF(OR(J9="",H9=""),"",J9*G9-H9-N(K9)) | M9: =IF(L9="","",L9/H9) | N9: =IF(OR(L9="",E9="",D9<=E9),"",L9/((D9-E9)*G9)) | O9: =IF(OR(D9="",E9="",F9="",D9<=E9),"",(F9-D9)/(D9-E9))
A10: 6 | H10: =IF(OR(D10="",G10=""),"",D10*G10) | L10: =IF(OR(J10="",H10=""),"",J10*G10-H10-N(K10)) | M10: =IF(L10="","",L10/H10) | N10: =IF(OR(L10="",E10="",D10<=E10),"",L10/((D10-E10)*G10)) | O10: =IF(OR(D10="",E10="",F10="",D10<=E10),"",(F10-D10)/(D10-E10))
A11: 7 | H11: =IF(OR(D11="",G11=""),"",D11*G11) | L11: =IF(OR(J11="",H11=""),"",J11*G11-H11-N(K11)) | M11: =IF(L11="","",L11/H11) | N11: =IF(OR(L11="",E11="",D11<=E11),"",L11/((D11-E11)*G11)) | O11: =IF(OR(D11="",E11="",F11="",D11<=E11),"",(F11-D11)/(D11-E11))
A12: 8 | H12: =IF(OR(D12="",G12=""),"",D12*G12) | L12: =IF(OR(J12="",H12=""),"",J12*G12-H12-N(K12)) | M12: =IF(L12="","",L12/H12) | N12: =IF(OR(L12="",E12="",D12<=E12),"",L12/((D12-E12)*G12)) | O12: =IF(OR(D12="",E12="",F12="",D12<=E12),"",(F12-D12)/(D12-E12))
A13: 9 | H13: =IF(OR(D13="",G13=""),"",D13*G13) | L13: =IF(OR(J13="",H13=""),"",J13*G13-H13-N(K13)) | M13: =IF(L13="","",L13/H13) | N13: =IF(OR(L13="",E13="",D13<=E13),"",L13/((D13-E13)*G13)) | O13: =IF(OR(D13="",E13="",F13="",D13<=E13),"",(F13-D13)/(D13-E13))
A14: 10 | H14: =IF(OR(D14="",G14=""),"",D14*G14) | L14: =IF(OR(J14="",H14=""),"",J14*G14-H14-N(K14)) | M14: =IF(L14="","",L14/H14) | N14: =IF(OR(L14="",E14="",D14<=E14),"",L14/((D14-E14)*G14)) | O14: =IF(OR(D14="",E14="",F14="",D14<=E14),"",(F14-D14)/(D14-E14))
A15: 11 | H15: =IF(OR(D15="",G15=""),"",D15*G15) | L15: =IF(OR(J15="",H15=""),"",J15*G15-H15-N(K15)) | M15: =IF(L15="","",L15/H15) | N15: =IF(OR(L15="",E15="",D15<=E15),"",L15/((D15-E15)*G15)) | O15: =IF(OR(D15="",E15="",F15="",D15<=E15),"",(F15-D15)/(D15-E15))
A16: 12 | H16: =IF(OR(D16="",G16=""),"",D16*G16) | L16: =IF(OR(J16="",H16=""),"",J16*G16-H16-N(K16)) | M16: =IF(L16="","",L16/H16) | N16: =IF(OR(L16="",E16="",D16<=E16),"",L16/((D16-E16)*G16)) | O16: =IF(OR(D16="",E16="",F16="",D16<=E16),"",(F16-D16)/(D16-E16))
A17: 13 | H17: =IF(OR(D17="",G17=""),"",D17*G17) | L17: =IF(OR(J17="",H17=""),"",J17*G17-H17-N(K17)) | M17: =IF(L17="","",L17/H17) | N17: =IF(OR(L17="",E17="",D17<=E17),"",L17/((D17-E17)*G17)) | O17: =IF(OR(D17="",E17="",F17="",D17<=E17),"",(F17-D17)/(D17-E17))
... A204: 200 | H204: =IF(OR(D204="",G204=""),"",D204*G204) | L204: =IF(OR(J204="",H204=""),"",J204*G204-H204-N(K204)) | M204: =IF(L204="","",L204/H204) | N204: =IF(OR(L204="",E204="",D204<=E204),"",L204/((D204-E204)*G204)) | O204: =IF(OR(D204="",E204="",F204="",D204<=E204),"",(F204-D204)/(D204-E204))

Sheet Summary
A1: Performance Summary
A2: Only closed trades (with an Exit Price) are counted.
A4: Starting balance ($) | B4: 50 | C4: Your original investment (from you).
A5: Closed trades | B5: =COUNT('Trade Journal'!$L$5:$L$204) -> 1
A6: Winners | B6: =COUNTIF('Trade Journal'!$L$5:$L$204,">0") -> 1
A7: Losers | B7: =COUNTIF('Trade Journal'!$L$5:$L$204,"<0") -> 0
A8: Win rate | B8: =IFERROR(B6/B5,0) -> 1
A9: Net P/L ($) | B9: =SUM('Trade Journal'!$L$5:$L$204) -> 28.996815
A10: Current balance ($) | B10: =B4+B9 -> 78.996815
A11: Total return on starting balance | B11: =IFERROR(B9/B4,0) -> 0.5799363
A12: Average win ($) | B12: =IFERROR(AVERAGEIF('Trade Journal'!$L$5:$L$204,">0"),0) -> 28.996815
A13: Average loss ($) | B13: =IFERROR(AVERAGEIF('Trade Journal'!$L$5:$L$204,"<0"),0) -> 0
A14: Profit factor (gross wins ÷ gross losses) | B14: =IF(B7=0,"No losses yet",SUMIF('Trade Journal'!$L$5:$L$204,">0")/-SUMIF('Trade Journal'!$L$5:$L$204,"<0")) -> No losses yet
A15: Average R multiple | B15: =IFERROR(AVERAGE('Trade Journal'!$N$5:$N$204),0) -> 5.9793103
A16: Largest win ($) | B16: =MAX(0,MAX('Trade Journal'!$L$5:$L$204)) -> 28.996815
A17: Largest loss ($) | B17: =MIN(0,MIN('Trade Journal'!$L$5:$L$204)) -> 0
A18: Trades where plan was followed | B18: =IFERROR(COUNTIF('Trade Journal'!$Q$5:$Q$204,"Y")/COUNTA('Trade Journal'!$Q$5:$Q$204),0) -> 1
A20: How to read it
A21: • Profit factor above 1.5 and average R above 0.3 after ~20 trades suggests a real edge.
A22: • A high win rate with a profit factor below 1 means your losses are bigger than your wins — tighten stops.
A23: • If 'plan followed' is low, the problem is discipline, not the strategy.

Sheet Meme Coin Checklist
A1: Meme Coin Pre-Trade Checklist
A2: Fill in one row BEFORE every Solana meme-coin buy. Answer Y or N in the blue columns. Verdict is GO only if every check is Y. Row 6 is an example.
A3: Rules: $5 per trade · max 3 trades/day · sell half at 2x · exit everything at -50% or if dev sells · never re-buy a coin after a loss.
A5: Date | B5: Coin | C5: Contract Address | D5: Mint Revoked? | E5: Freeze Revoked? | F5: Top 10 < 30%? | G5: No Bundled Launch? | H5: Dev Not Selling? | I5: Age ≥ 30 min? | J5: Holders ≥ 200? | K5: Size ≤ $5? | L5: ≤ 3 Trades Today? | M5: Checks Passed | N5: Verdict | O5: Notes
A6: 46312 | B6: EXAMPLE | C6: (paste from RugCheck) | D6: Y | E6: Y | F6: N | G6: Y | H6: Y | I6: Y | J6: Y | K6: Y | L6: Y | M6: =IF(B6="","",COUNTIF(D6:L6,"Y")&"/9") -> 8/9 | N6: =IF(B6="","",IF(COUNTIF(D6:L6,"Y")=9,"GO","NO-GO")) -> NO-GO | O6: Top 10 hold 41% — skip it. Example row; delete or overwrite.
M7: =IF(B7="","",COUNTIF(D7:L7,"Y")&"/9") | N7: =IF(B7="","",IF(COUNTIF(D7:L7,"Y")=9,"GO","NO-GO"))
M8: =IF(B8="","",COUNTIF(D8:L8,"Y")&"/9") | N8: =IF(B8="","",IF(COUNTIF(D8:L8,"Y")=9,"GO","NO-GO"))
M9: =IF(B9="","",COUNTIF(D9:L9,"Y")&"/9") | N9: =IF(B9="","",IF(COUNTIF(D9:L9,"Y")=9,"GO","NO-GO"))
M10: =IF(B10="","",COUNTIF(D10:L10,"Y")&"/9") | N10: =IF(B10="","",IF(COUNTIF(D10:L10,"Y")=9,"GO","NO-GO"))
M11: =IF(B11="","",COUNTIF(D11:L11,"Y")&"/9") | N11: =IF(B11="","",IF(COUNTIF(D11:L11,"Y")=9,"GO","NO-GO"))
M12: =IF(B12="","",COUNTIF(D12:L12,"Y")&"/9") | N12: =IF(B12="","",IF(COUNTIF(D12:L12,"Y")=9,"GO","NO-GO"))
M13: =IF(B13="","",COUNTIF(D13:L13,"Y")&"/9") | N13: =IF(B13="","",IF(COUNTIF(D13:L13,"Y")=9,"GO","NO-GO"))
M14: =IF(B14="","",COUNTIF(D14:L14,"Y")&"/9") | N14: =IF(B14="","",IF(COUNTIF(D14:L14,"Y")=9,"GO","NO-GO"))
M15: =IF(B15="","",COUNTIF(D15:L15,"Y")&"/9") | N15: =IF(B15="","",IF(COUNTIF(D15:L15,"Y")=9,"GO","NO-GO"))
M16: =IF(B16="","",COUNTIF(D16:L16,"Y")&"/9") | N16: =IF(B16="","",IF(COUNTIF(D16:L16,"Y")=9,"GO","NO-GO"))
M17: =IF(B17="","",COUNTIF(D17:L17,"Y")&"/9") | N17: =IF(B17="","",IF(COUNTIF(D17:L17,"Y")=9,"GO","NO-GO"))
M18: =IF(B18="","",COUNTIF(D18:L18,"Y")&"/9") | N18: =IF(B18="","",IF(COUNTIF(D18:L18,"Y")=9,"GO","NO-GO"))
... M205: =IF(B205="","",COUNTIF(D205:L205,"Y")&"/9") | N205: =IF(B205="","",IF(COUNTIF(D205:L205,"Y")=9,"GO","NO-GO"))

Sheet Polymarket Log
A1: Polymarket Log
A2: Write YOUR probability before looking at the price. Prices are entered as cents (e.g. 42 for 42¢). Outcome: Won / Lost / Open. Row 9 is an example.
A4: Starting budget ($) | B4: 9 | C4: From the plan: $9 of your $29 experiment budget. | E4: Net P/L ($) | F4: =SUM(N9:N208) -> 0 | G4: Calibration (Brier score) | H4: =IFERROR(SUMPRODUCT((L9:L208="Won")*(1-E9:E208)^2+(L9:L208="Lost")*(E9:E208)^2)/(COUNTIF(L9:L208,"Won")+COUNTIF(L9:L208,"Lost")),"") | I4: Lower is better: 0.25 = coin-flip guessing, under 0.20 = some skill.
A5: Min edge to bet (percentage points) | B5: 10 | C5: Only bet when your estimate beats the market price by at least this much. | E5: Balance ($) | F5: =B4+F4 -> 9 | G5: Bets that met the rules | H5: =IFERROR(COUNTIF(J9:J208,"YES")/COUNTA(B9:B208),0) -> 1
E6: Win rate (resolved) | F6: =IFERROR(COUNTIF(L9:L208,"Won")/(COUNTIF(L9:L208,"Won")+COUNTIF(L9:L208,"Lost")),0) -> 0
A8: Date | B8: Market / Question | C8: Niche | D8: Side (YES/NO) | E8: Your Prob. Your Side Wins | F8: Price Paid (¢) | G8: Edge (pts) | H8: Stake ($) | I8: Shares | J8: Meets Rules? | K8: Reasoning | L8: Outcome | M8: Resolved Date | N8: P/L ($) | O8: Lesson
A9: 46312 | B9: EXAMPLE — Will [team] win Sunday's game? | C9: Sports | D9: YES | E9: 0.6 | F9: 45 | G9: =IF(OR(E9="",F9=""),"",E9*100-F9) -> 15 | H9: 2 | I9: =IF(OR(H9="",F9="",N(F9)=0),"",H9/(F9/100)) -> 4.4444444 | J9: =IF(G9="","",IF(AND(G9>=$B$5,F9>=5,F9<=95),"YES","NO")) -> YES | K9: Starting QB back from injury; market hasn't adjusted. | L9: Open | N9: =IF(L9="Won",I9-H9,IF(L9="Lost",-H9,"")) | O9: Example row; delete or overwrite.
G10: =IF(OR(E10="",F10=""),"",E10*100-F10) | I10: =IF(OR(H10="",F10="",N(F10)=0),"",H10/(F10/100)) | J10: =IF(G10="","",IF(AND(G10>=$B$5,F10>=5,F10<=95),"YES","NO")) | N10: =IF(L10="Won",I10-H10,IF(L10="Lost",-H10,""))
G11: =IF(OR(E11="",F11=""),"",E11*100-F11) | I11: =IF(OR(H11="",F11="",N(F11)=0),"",H11/(F11/100)) | J11: =IF(G11="","",IF(AND(G11>=$B$5,F11>=5,F11<=95),"YES","NO")) | N11: =IF(L11="Won",I11-H11,IF(L11="Lost",-H11,""))
G12: =IF(OR(E12="",F12=""),"",E12*100-F12) | I12: =IF(OR(H12="",F12="",N(F12)=0),"",H12/(F12/100)) | J12: =IF(G12="","",IF(AND(G12>=$B$5,F12>=5,F12<=95),"YES","NO")) | N12: =IF(L12="Won",I12-H12,IF(L12="Lost",-H12,""))
G13: =IF(OR(E13="",F13=""),"",E13*100-F13) | I13: =IF(OR(H13="",F13="",N(F13)=0),"",H13/(F13/100)) | J13: =IF(G13="","",IF(AND(G13>=$B$5,F13>=5,F13<=95),"YES","NO")) | N13: =IF(L13="Won",I13-H13,IF(L13="Lost",-H13,""))
G14: =IF(OR(E14="",F14=""),"",E14*100-F14) | I14: =IF(OR(H14="",F14="",N(F14)=0),"",H14/(F14/100)) | J14: =IF(G14="","",IF(AND(G14>=$B$5,F14>=5,F14<=95),"YES","NO")) | N14: =IF(L14="Won",I14-H14,IF(L14="Lost",-H14,""))
G15: =IF(OR(E15="",F15=""),"",E15*100-F15) | I15: =IF(OR(H15="",F15="",N(F15)=0),"",H15/(F15/100)) | J15: =IF(G15="","",IF(AND(G15>=$B$5,F15>=5,F15<=95),"YES","NO")) | N15: =IF(L15="Won",I15-H15,IF(L15="Lost",-H15,""))
G16: =IF(OR(E16="",F16=""),"",E16*100-F16) | I16: =IF(OR(H16="",F16="",N(F16)=0),"",H16/(F16/100)) | J16: =IF(G16="","",IF(AND(G16>=$B$5,F16>=5,F16<=95),"YES","NO")) | N16: =IF(L16="Won",I16-H16,IF(L16="Lost",-H16,""))
G17: =IF(OR(E17="",F17=""),"",E17*100-F17) | I17: =IF(OR(H17="",F17="",N(F17)=0),"",H17/(F17/100)) | J17: =IF(G17="","",IF(AND(G17>=$B$5,F17>=5,F17<=95),"YES","NO")) | N17: =IF(L17="Won",I17-H17,IF(L17="Lost",-H17,""))
G18: =IF(OR(E18="",F18=""),"",E18*100-F18) | I18: =IF(OR(H18="",F18="",N(F18)=0),"",H18/(F18/100)) | J18: =IF(G18="","",IF(AND(G18>=$B$5,F18>=5,F18<=95),"YES","NO")) | N18: =IF(L18="Won",I18-H18,IF(L18="Lost",-H18,""))
G19: =IF(OR(E19="",F19=""),"",E19*100-F19) | I19: =IF(OR(H19="",F19="",N(F19)=0),"",H19/(F19/100)) | J19: =IF(G19="","",IF(AND(G19>=$B$5,F19>=5,F19<=95),"YES","NO")) | N19: =IF(L19="Won",I19-H19,IF(L19="Lost",-H19,""))
G20: =IF(OR(E20="",F20=""),"",E20*100-F20) | I20: =IF(OR(H20="",F20="",N(F20)=0),"",H20/(F20/100)) | J20: =IF(G20="","",IF(AND(G20>=$B$5,F20>=5,F20<=95),"YES","NO")) | N20: =IF(L20="Won",I20-H20,IF(L20="Lost",-H20,""))
G21: =IF(OR(E21="",F21=""),"",E21*100-F21) | I21: =IF(OR(H21="",F21="",N(F21)=0),"",H21/(F21/100)) | J21: =IF(G21="","",IF(AND(G21>=$B$5,F21>=5,F21<=95),"YES","NO")) | N21: =IF(L21="Won",I21-H21,IF(L21="Lost",-H21,""))
... G208: =IF(OR(E208="",F208=""),"",E208*100-F208) | I208: =IF(OR(H208="",F208="",N(F208)=0),"",H208/(F208/100)) | J208: =IF(G208="","",IF(AND(G208>=$B$5,F208>=5,F208<=95),"YES","NO")) | N208: =IF(L208="Won",I208-H208,IF(L208="Lost",-H208,""))
